<archetype>
    <id>crucible-plugin-archetype</id>
    <sources>
        <source>src/main/java/ExampleServlet.java</source>
    </sources>
    <testSources>
    </testSources>

    <resources>
        <resource filtered="true">src/main/resources/atlassian-plugin.xml</resource>
        <resource filtered="false">src/test/resources/TEST_RESOURCES_README.txt</resource>
        <resource filtered="false">README.txt</resource>
        <resource filtered="false">LICENSE.TXT</resource>
    </resources>
</archetype>
